coinwoke/__init__.py
coinwoke/index.py
coinwoke-0.0.1.dist-info/DESCRIPTION.rst
coinwoke-0.0.1.dist-info/METADATA
coinwoke-0.0.1.dist-info/RECORD
coinwoke-0.0.1.dist-info/WHEEL
coinwoke-0.0.1.dist-info/metadata.json
coinwoke-0.0.1.dist-info/top_level.txt
