Metadata-Version: 2.0
Name: coinwoke
Version: 0.0.1
Summary: All things cryptocurrency.
Home-page: UNKNOWN
Author: UNKNOWN
Author-email: UNKNOWN
License: MIT
Platform: UNKNOWN
